schemasync/__init__.py
schemasync/schemasync.py
schemasync/syncdb.py
schemasync/utils.py
SchemaSync_h-0.9.6.dist-info/LICENSE
SchemaSync_h-0.9.6.dist-info/METADATA
SchemaSync_h-0.9.6.dist-info/WHEEL
SchemaSync_h-0.9.6.dist-info/entry_points.txt
SchemaSync_h-0.9.6.dist-info/top_level.txt
SchemaSync_h-0.9.6.dist-info/RECORD
