Metadata-Version: 2.1
Name: SchemaSync-h
Version: 0.9.6
Summary: A MySQL Schema Synchronization Utility
Home-page: UNKNOWN
Author: Mitch Matuson, Mustafa Ozgur
Author-email: UNKNOWN
License: UNKNOWN
Keywords: MySQL,database,schema,migration,SQL
Platform: UNKNOWN
Classifier: Environment :: Console
Classifier: Intended Audience :: Information Technology
Classifier: Intended Audience :: System Administrators
Classifier: Intended Audience :: Developers
Classifier: License :: OSI Approved :: Apache Software License
Classifier: Programming Language :: Python
Classifier: Topic :: Database
Classifier: Topic :: Database :: Front-Ends
Classifier: Topic :: Software Development :: Build Tools
Classifier: Topic :: Software Development :: Code Generators
Classifier: Topic :: Utilities
Requires-Dist: SchemaObject (>=0.5.7)
